{
  "SerializedFilePath": "c:\\Users\\Dell Vostro\\Documents\\תיכנות\\שנה ב\\Core\\project\\MyTasks\\obj\\Debug\\net7.0\\project.razor.json",
  "FilePath": "c:\\Users\\Dell Vostro\\Documents\\תיכנות\\שנה ב\\Core\\project\\MyTasks\\MyTasks.csproj",
  "Configuration": {
    "ConfigurationName": "MVC-3.0",
    "LanguageVersion": "6.0",
    "Extensions": [
      {
        "ExtensionName": "MVC-3.0"
      }
    ]
  },
  "ProjectWorkspaceState": {
    "TagHelpers": [],
    "CSharpLanguageVersion": 1100
  },
  "RootNamespace": "MyTasks",
  "Documents": [],
  "SerializationFormat": "0.3"
}